blml1/__init__.py
blml1/_common/__init__.py
blml1-0.16.0.data/data/LICENSE.txt
blml1-0.16.0.dist-info/LICENSE.txt
blml1-0.16.0.dist-info/METADATA
blml1-0.16.0.dist-info/WHEEL
blml1-0.16.0.dist-info/top_level.txt
blml1-0.16.0.dist-info/zip-safe
blml1-0.16.0.dist-info/RECORD
