Metadata-Version: 2.1
Name: blml1
Version: 0.16.0
Summary: blml1
Home-page: https://github.com/kshramt/blml1
Author: kshramt
License: UNKNOWN
Platform: UNKNOWN
Classifier: License :: OSI Approved :: GNU General Public License v3 (GPLv3)
Requires-Dist: lightgbm
Requires-Dist: numba
Requires-Dist: numpy
Requires-Dist: optuna
Requires-Dist: tensorflow
Provides-Extra: dev
Requires-Dist: black ; extra == 'dev'
Requires-Dist: ipython ; extra == 'dev'
Requires-Dist: mypy ; extra == 'dev'
Requires-Dist: pyflakes ; extra == 'dev'
Requires-Dist: pylint ; extra == 'dev'
Requires-Dist: pytest ; extra == 'dev'
Requires-Dist: pytype ; extra == 'dev'
Requires-Dist: twine ; extra == 'dev'
Requires-Dist: wheel ; extra == 'dev'
Requires-Dist: coverage ; extra == 'dev'
